baseball_Info/__init__.py
baseball_Info/player.py
baseball_Info/team.py
Baseball_Inform-0.0.0.2.dist-info/METADATA
Baseball_Inform-0.0.0.2.dist-info/WHEEL
Baseball_Inform-0.0.0.2.dist-info/top_level.txt
Baseball_Inform-0.0.0.2.dist-info/RECORD
