Metadata-Version: 2.1
Name: Baseball-Inform
Version: 0.0.0.2
Summary: baseball API
Home-page: 
Author: basekk
Author-email: jino152637@gmail.com
License: MIT
Requires-Python: >=3.4
